scope3ai/__init__.py
scope3ai/lib.py
scope3ai/worker.py
scope3ai/api/__init__.py
scope3ai/api/client.py
scope3ai/api/defaults.py
scope3ai/api/types.py
scope3ai/api/typesgen.py
scope3ai/tracers/anthropic/chat.py
scope3ai/tracers/anthropic/instrument.py
scope3ai/tracers/huggingface/chat.py
scope3ai/tracers/huggingface/instrument.py
scope3ai/tracers/huggingface/speech_to_text.py
scope3ai/tracers/huggingface/text_to_image.py
scope3ai/tracers/huggingface/text_to_speech.py
scope3ai/tracers/huggingface/translation.py
scope3ai/tracers/huggingface/utils.py
scope3ai/tracers/mistralai/instrument.py
scope3ai/tracers/openai/chat.py
scope3ai/tracers/openai/instrument.py
scope3ai_py-0.1.0a2.dist-info/METADATA
scope3ai_py-0.1.0a2.dist-info/WHEEL
scope3ai_py-0.1.0a2.dist-info/top_level.txt
scope3ai_py-0.1.0a2.dist-info/RECORD
