Metadata-Version: 2.1
Name: scope3ai-py
Version: 0.1.0a2
Summary: Track the environmental impact of your use of AI
Requires-Python: >=3.9
Requires-Dist: httpx>=0.28.1
Requires-Dist: huggingface-hub>=0.26.5
Requires-Dist: litellm>=1.53.3
Requires-Dist: pillow>=11.0.0
Requires-Dist: pydantic>=2.10.3
Requires-Dist: wrapt>=1.17.0
Provides-Extra: openai
Requires-Dist: openai>=1.57.1; extra == "openai"
Provides-Extra: litellm
Requires-Dist: litellm>=1.53.3; extra == "litellm"
Requires-Dist: rapidfuzz>=3.10.1; extra == "litellm"
Provides-Extra: mistralai
Requires-Dist: mistralai>=0.4.2; extra == "mistralai"
Provides-Extra: anthropic
Requires-Dist: anthropic>=0.40.0; extra == "anthropic"
Provides-Extra: cohere
Requires-Dist: cohere>=5.13.3; extra == "cohere"
Provides-Extra: huggingface-hub
Requires-Dist: aiohttp>=3.11.10; extra == "huggingface-hub"
Requires-Dist: huggingface-hub>=0.26.5; extra == "huggingface-hub"
Requires-Dist: minijinja>=2.5.0; extra == "huggingface-hub"
Requires-Dist: tiktoken>=0.8.0; extra == "huggingface-hub"
Provides-Extra: google-generativeai
Requires-Dist: google-generativeai>=0.8.3; extra == "google-generativeai"
